{
  "version": 1,
  "base_track": "Down with the Sickness",
  "base_artist": "Disturbed",
  "createdAt": "2026-02-17T14:47:59.670714Z",
  "candidates": [
    {
      "id": "lrclib_1",
      "source": "lrclib",
      "title": "Down With The Sickness",
      "artist": "Disturbed",
      "has_synced": true,
      "path": "select/01_Down_With_The_Sickness_Disturbed.lrc"
    },
    {
      "id": "lrclib_2",
      "source": "lrclib",
      "title": "Down With the Sickness",
      "artist": "Disturbed",
      "has_synced": true,
      "path": "select/02_Down_With_the_Sickness_Disturbed.lrc"
    },
    {
      "id": "lrclib_3",
      "source": "lrclib",
      "title": "Down With The Sickness",
      "artist": "Disturbed",
      "has_synced": true,
      "path": "select/03_Down_With_The_Sickness_Disturbed.lrc"
    },
    {
      "id": "lrclib_4",
      "source": "lrclib",
      "title": "Down with the Sickness",
      "artist": "Disturbed",
      "has_synced": true,
      "path": "select/04_Down_with_the_Sickness_Disturbed.lrc"
    },
    {
      "id": "lrclib_5",
      "source": "lrclib",
      "title": "Down with the Sickness",
      "artist": "Disturbed",
      "has_synced": false,
      "path": "select/05_Down_with_the_Sickness_Disturbed.txt"
    },
    {
      "id": "petitlyrics_1",
      "source": "petitlyrics",
      "title": "Down With The Sickness",
      "artist": "Disturbed",
      "has_synced": false,
      "path": "select/pl_01_Down_With_The_Sickness_Disturbed.txt"
    }
  ]
}